odoo/addons/mrp_workcenter_hierarchical/README.rst
odoo/addons/mrp_workcenter_hierarchical/__init__.py
odoo/addons/mrp_workcenter_hierarchical/__manifest__.py
odoo/addons/mrp_workcenter_hierarchical/data/mrp_demo.xml
odoo/addons/mrp_workcenter_hierarchical/i18n/it.po
odoo/addons/mrp_workcenter_hierarchical/i18n/mrp_workcenter_hierarchical.pot
odoo/addons/mrp_workcenter_hierarchical/models/__init__.py
odoo/addons/mrp_workcenter_hierarchical/models/mrp_workcenter.py
odoo/addons/mrp_workcenter_hierarchical/readme/CONFIGURE.rst
odoo/addons/mrp_workcenter_hierarchical/readme/CONTRIBUTORS.rst
odoo/addons/mrp_workcenter_hierarchical/readme/DESCRIPTION.rst
odoo/addons/mrp_workcenter_hierarchical/readme/USAGE.rst
odoo/addons/mrp_workcenter_hierarchical/static/description/icon.png
odoo/addons/mrp_workcenter_hierarchical/static/description/index.html
odoo/addons/mrp_workcenter_hierarchical/static/src/img/icon.png
odoo/addons/mrp_workcenter_hierarchical/static/src/img/img1.png
odoo/addons/mrp_workcenter_hierarchical/tests/__init__.py
odoo/addons/mrp_workcenter_hierarchical/tests/test_compute_level.py
odoo/addons/mrp_workcenter_hierarchical/views/workcenter_view.xml
odoo14_addon_mrp_workcenter_hierarchical-14.0.1.0.1.dist-info/METADATA
odoo14_addon_mrp_workcenter_hierarchical-14.0.1.0.1.dist-info/WHEEL
odoo14_addon_mrp_workcenter_hierarchical-14.0.1.0.1.dist-info/top_level.txt
odoo14_addon_mrp_workcenter_hierarchical-14.0.1.0.1.dist-info/RECORD
